odoo8_addon_l10n_nl_tax_declaration_reporting-8.0.1.0.0-py2.7-nspkg.pth
odoo_addons/l10n_nl_tax_declaration_reporting/__openerp__.py
odoo_addons/l10n_nl_tax_declaration_reporting/__init__.py
odoo_addons/l10n_nl_tax_declaration_reporting/README.rst
odoo_addons/l10n_nl_tax_declaration_reporting/report/__init__.py
odoo_addons/l10n_nl_tax_declaration_reporting/report/report_vat.py
odoo_addons/l10n_nl_tax_declaration_reporting/i18n/l10n_nl_addon.pot
odoo_addons/l10n_nl_tax_declaration_reporting/i18n/nl.po
odoo_addons/l10n_nl_tax_declaration_reporting/i18n/en_US.po
odoo_addons/l10n_nl_tax_declaration_reporting/wizard/__init__.py
odoo_addons/l10n_nl_tax_declaration_reporting/wizard/account_vat_view_nl.xml
odoo_addons/l10n_nl_tax_declaration_reporting/wizard/account_vat.py
odoo_addons/l10n_nl_tax_declaration_reporting/views/account_tax_report.xml
odoo8_addon_l10n_nl_tax_declaration_reporting-8.0.1.0.0.dist-info/top_level.txt
odoo8_addon_l10n_nl_tax_declaration_reporting-8.0.1.0.0.dist-info/WHEEL
odoo8_addon_l10n_nl_tax_declaration_reporting-8.0.1.0.0.dist-info/RECORD
odoo8_addon_l10n_nl_tax_declaration_reporting-8.0.1.0.0.dist-info/metadata.json
odoo8_addon_l10n_nl_tax_declaration_reporting-8.0.1.0.0.dist-info/DESCRIPTION.rst
odoo8_addon_l10n_nl_tax_declaration_reporting-8.0.1.0.0.dist-info/METADATA
odoo8_addon_l10n_nl_tax_declaration_reporting-8.0.1.0.0.dist-info/namespace_packages.txt
